paint_with_words/__init__.py
paint_with_words/helper/__Init__.py
paint_with_words/helper/aliases.py
paint_with_words/helper/images.py
paint_with_words/models/__init__.py
paint_with_words/models/attention_processor.py
paint_with_words/pipelines/__init__.py
paint_with_words/pipelines/paint_with_words_pipeline.py
paint_with_words/weight_functions.py
paint_with_words_pipeline-1.0.1.dist-info/LICENSE
paint_with_words_pipeline-1.0.1.dist-info/METADATA
paint_with_words_pipeline-1.0.1.dist-info/WHEEL
paint_with_words_pipeline-1.0.1.dist-info/RECORD
