Metadata-Version: 2.1
Name: paint-with-words-pipeline
Version: 1.0.1
Summary: 
Author: Simo Ryu
Author-email: cloneofsimo@gmail.com
Requires-Python: >=3.9,<3.13
Classifier: Programming Language :: Python :: 3
Classifier: Programming Language :: Python :: 3.9
Classifier: Programming Language :: Python :: 3.10
Classifier: Programming Language :: Python :: 3.11
Requires-Dist: accelerate (>=0.21.0,<0.22.0)
Requires-Dist: diffusers (>=0.19.3,<0.20.0)
Requires-Dist: ftfy (>=6.1.1,<7.0.0)
Requires-Dist: scipy (>=1.11.1,<2.0.0)
Requires-Dist: torch (>=2.0.0,!=2.0.1)
Requires-Dist: torchvision (>=0.15.1,<0.16.0)
Requires-Dist: transformers (>=4.31.0,<5.0.0)
